nqdb/__init__.py
nqdb/cache.py
nqdb/client.py
nqdb/datastore_client.py
nqdb/datastore_mock.py
nqdb/key.py
nqdb/model.py
nqdb/nqdb_ops.py
nqdb/property.py
nqdb/query.py
nqdb-0.1.0.dist-info/LICENSE.md
nqdb-0.1.0.dist-info/METADATA
nqdb-0.1.0.dist-info/WHEEL
nqdb-0.1.0.dist-info/top_level.txt
nqdb-0.1.0.dist-info/RECORD
