Metadata-Version: 2.1
Name: nqdb
Version: 0.1.0
Summary: Interface to Google Datastore, mimicking aspects of ndb, but allowing for different backends and caching
Home-page: https://bitbucket.org/luca_de_alfaro/nqdb
Author: Luca de Alfaro
Author-email: dealfaro@alumni.stanford.edu
Maintainer: Luca de Alfaro
Maintainer-email: dealfaro@alumni.stanford.edu
License: BSD
Platform: any
Classifier: Development Status :: 3 - Alpha
Classifier: Intended Audience :: Developers
Classifier: License :: OSI Approved :: BSD License
Classifier: Operating System :: OS Independent
Classifier: Programming Language :: Python
Classifier: Programming Language :: Python :: Implementation :: CPython
Classifier: Topic :: Software Development :: Libraries :: Python Modules
Requires-Python: >=3.7
Requires-Dist: functools
Requires-Dist: google.cloud.datastore
Requires-Dist: uuid
Requires-Dist: contextlib
Requires-Dist: json
Requires-Dist: numbers
Requires-Dist: datetime
Requires-Dist: pytz
Requires-Dist: zlib
Requires-Dist: base64
